{
  "path": "apps/android/app/src/main/java/ai/openclaw/app/node/A2UIHandler.kt",
  "extension": ".kt",
  "size_bytes": 4754,
  "line_count": 146,
  "documentation": {
    "file_docstring": null,
    "header_comments": [],
    "inline_comments": [],
    "todo_comments": [],
    "has_readme_style_header": false
  },
  "purpose": {
    "primary_role": "controller",
    "secondary_roles": [],
    "confidence": 0.8,
    "indicators": [
      "controller/handler path"
    ]
  },
  "exports": [],
  "imports": {
    "internal": [],
    "external": [],
    "standard": []
  },
  "functions": [],
  "classes": [],
  "complexity_score": 24,
  "responsibility": {
    "single_responsibility_score": 0.6,
    "cohesion_indicators": [],
    "concerns": [
      "Multiple concerns detected: ui, api, business_logic, logging"
    ],
    "detected_concerns": [
      "ui",
      "api",
      "business_logic",
      "logging"
    ]
  }
}