{
  "path": "extensions/whatsapp/src/auto-reply/monitor/on-message.ts",
  "extension": ".ts",
  "size_bytes": 5920,
  "line_count": 170,
  "documentation": {
    "file_docstring": null,
    "header_comments": [],
    "inline_comments": [
      "Fresh config for bindings lookup; other routing inputs are payload-derived.",
      "Same-phone mode logging retained",
      "Skip if this is a message we just sent (echo detection)",
      "Ensure `peerId` for DMs is stable and stored as E.164 when possible.",
      "Broadcast groups: when we'd reply anyway, run multiple agents.",
      "Does not bypass group mention/activation gating above."
    ],
    "todo_comments": [],
    "has_readme_style_header": false
  },
  "purpose": {
    "primary_role": "unknown",
    "secondary_roles": [],
    "confidence": 0.0,
    "indicators": []
  },
  "exports": [
    "createWebOnMessageHandler"
  ],
  "imports": {
    "internal": [
      "../mentions.js",
      "../types.js",
      "./broadcast.js",
      "./echo.js",
      "./group-gating.js",
      "./group-gating.js",
      "./last-route.js",
      "./peer.js",
      "./process-message.js"
    ],
    "external": [
      "openclaw/plugin-sdk/config-runtime",
      "openclaw/plugin-sdk/reply-runtime",
      "openclaw/plugin-sdk/reply-runtime",
      "openclaw/plugin-sdk/routing",
      "openclaw/plugin-sdk/routing",
      "openclaw/plugin-sdk/runtime-env",
      "openclaw/plugin-sdk/text-runtime"
    ],
    "standard": []
  },
  "functions": [
    {
      "name": "createWebOnMessageHandler",
      "line": 18,
      "doc": "No documentation",
      "is_public": true,
      "is_async": false
    }
  ],
  "classes": [],
  "complexity_score": 13,
  "responsibility": {
    "single_responsibility_score": 0.6,
    "cohesion_indicators": [],
    "concerns": [
      "Multiple concerns detected: api, business_logic, auth, logging"
    ],
    "detected_concerns": [
      "api",
      "business_logic",
      "auth",
      "logging"
    ]
  }
}