{
  "path": "extensions/feishu/src/reactions.ts",
  "extension": ".ts",
  "size_bytes": 4346,
  "line_count": 153,
  "documentation": {
    "file_docstring": null,
    "header_comments": [],
    "inline_comments": [
      "Add a reaction (emoji) to a message. @param emojiType - Feishu emoji type, e.g., \"SMILE\", \"THUMBSUP\", \"HEART\" @see https://open.feishu.cn/document/server-docs/im-v1/message-reaction/emojis-introduce",
      "Remove a reaction from a message.",
      "List all reactions for a message.",
      "Common Feishu emoji types for convenience. @see https://open.feishu.cn/document/server-docs/im-v1/message-reaction/emojis-introduce",
      "Common reactions"
    ],
    "todo_comments": [],
    "has_readme_style_header": false
  },
  "purpose": {
    "primary_role": "unknown",
    "secondary_roles": [],
    "confidence": 0.0,
    "indicators": []
  },
  "exports": [
    "FeishuEmoji"
  ],
  "imports": {
    "internal": [
      "../runtime-api.js",
      "./accounts.js",
      "./client.js"
    ],
    "external": [],
    "standard": []
  },
  "functions": [
    {
      "name": "resolveConfiguredFeishuClient",
      "line": 12,
      "doc": "No documentation",
      "is_public": false,
      "is_async": false
    },
    {
      "name": "assertFeishuReactionApiSuccess",
      "line": 20,
      "doc": "No documentation",
      "is_public": false,
      "is_async": false
    },
    {
      "name": "addReactionFeishu",
      "line": 31,
      "doc": "Add a reaction (emoji) to a message.    emojiType - Feishu emoji type, e.g., \"SMILE\", \"THUMBSUP\", \"HEART\"    https:.feis",
      "is_public": true,
      "is_async": true
    },
    {
      "name": "removeReactionFeishu",
      "line": 66,
      "doc": "Remove a reaction from a message.",
      "is_public": true,
      "is_async": true
    },
    {
      "name": "listReactionsFeishu",
      "line": 88,
      "doc": "List all reactions for a message.",
      "is_public": true,
      "is_async": true
    }
  ],
  "classes": [
    {
      "name": "FeishuReaction",
      "line": 5,
      "doc": "No documentation",
      "is_public": true,
      "kind": "type_alias"
    },
    {
      "name": "FeishuEmojiType",
      "line": 153,
      "doc": "No documentation",
      "is_public": true,
      "kind": "type_alias"
    }
  ],
  "complexity_score": 11,
  "responsibility": {
    "single_responsibility_score": 1.0,
    "cohesion_indicators": [],
    "concerns": [],
    "detected_concerns": [
      "api",
      "logging"
    ]
  }
}