{
  "path": "src/cli/program/register.onboard.ts",
  "extension": ".ts",
  "size_bytes": 9177,
  "line_count": 202,
  "documentation": {
    "file_docstring": null,
    "header_comments": [],
    "inline_comments": [
      "Commander doesn't support option conflicts natively; keep original behavior.",
      "If --skip-daemon is explicitly passed, it wins."
    ],
    "todo_comments": [],
    "has_readme_style_header": false
  },
  "purpose": {
    "primary_role": "unknown",
    "secondary_roles": [],
    "confidence": 0.0,
    "indicators": []
  },
  "exports": [
    "registerOnboardCommand"
  ],
  "imports": {
    "internal": [
      "../../commands/auth-choice-options.js",
      "../../commands/daemon-runtime.js",
      "../../commands/onboard-core-auth-flags.js",
      "../../commands/onboard.js",
      "../../plugins/provider-auth-choices.js",
      "../../runtime.js",
      "../../terminal/links.js",
      "../../terminal/theme.js",
      "../cli-utils.js"
    ],
    "external": [
      "commander"
    ],
    "standard": []
  },
  "functions": [
    {
      "name": "resolveInstallDaemonFlag",
      "line": 21,
      "doc": "No documentation",
      "is_public": false,
      "is_async": false
    },
    {
      "name": "pickOnboardProviderAuthOptionValues",
      "line": 55,
      "doc": "No documentation",
      "is_public": false,
      "is_async": false
    },
    {
      "name": "registerOnboardCommand",
      "line": 63,
      "doc": "No documentation",
      "is_public": true,
      "is_async": false
    }
  ],
  "classes": [],
  "complexity_score": 12,
  "responsibility": {
    "single_responsibility_score": 1.0,
    "cohesion_indicators": [],
    "concerns": [],
    "detected_concerns": [
      "api",
      "auth"
    ]
  }
}