{
  "path": "src/plugins/provider-model-allowlist.ts",
  "extension": ".ts",
  "size_bytes": 970,
  "line_count": 41,
  "documentation": {
    "file_docstring": null,
    "header_comments": [],
    "inline_comments": [],
    "todo_comments": [],
    "has_readme_style_header": false
  },
  "purpose": {
    "primary_role": "data_model",
    "secondary_roles": [],
    "confidence": 0.8,
    "indicators": [
      "model/schema path"
    ]
  },
  "exports": [
    "ensureModelAllowlistEntry"
  ],
  "imports": {
    "internal": [
      "../agents/defaults.js",
      "../agents/model-selection.js",
      "../config/config.js"
    ],
    "external": [],
    "standard": []
  },
  "functions": [
    {
      "name": "ensureModelAllowlistEntry",
      "line": 5,
      "doc": "No documentation",
      "is_public": true,
      "is_async": false
    }
  ],
  "classes": [],
  "complexity_score": 4,
  "responsibility": {
    "single_responsibility_score": 1.0,
    "cohesion_indicators": [
      "Minimal mixed concerns"
    ],
    "concerns": [],
    "detected_concerns": []
  }
}