{
  "path": "src/gateway/server-methods/models.ts",
  "extension": ".ts",
  "size_bytes": 1253,
  "line_count": 39,
  "documentation": {
    "file_docstring": null,
    "header_comments": [],
    "inline_comments": [],
    "todo_comments": [],
    "has_readme_style_header": false
  },
  "purpose": {
    "primary_role": "data_model",
    "secondary_roles": [],
    "confidence": 0.8,
    "indicators": [
      "model/schema path"
    ]
  },
  "exports": [
    "modelsHandlers"
  ],
  "imports": {
    "internal": [
      "../../agents/defaults.js",
      "../../agents/model-selection.js",
      "../../config/config.js",
      "./types.js"
    ],
    "external": [],
    "standard": []
  },
  "functions": [],
  "classes": [],
  "complexity_score": 3,
  "responsibility": {
    "single_responsibility_score": 0.6,
    "cohesion_indicators": [],
    "concerns": [
      "Multiple concerns detected: api, business_logic, logging"
    ],
    "detected_concerns": [
      "api",
      "business_logic",
      "logging"
    ]
  }
}