{
  "path": "src/gateway/server-methods/skills.ts",
  "extension": ".ts",
  "size_bytes": 6425,
  "line_count": 204,
  "documentation": {
    "file_docstring": null,
    "header_comments": [],
    "inline_comments": [],
    "todo_comments": [],
    "has_readme_style_header": false
  },
  "purpose": {
    "primary_role": "unknown",
    "secondary_roles": [],
    "confidence": 0.0,
    "indicators": []
  },
  "exports": [
    "skillsHandlers"
  ],
  "imports": {
    "internal": [
      "../../agents/skills-install.js",
      "../../agents/skills-status.js",
      "../../agents/skills.js",
      "../../agents/workspace-dirs.js",
      "../../config/config.js",
      "../../config/config.js",
      "../../infra/skills-remote.js",
      "../../routing/session-key.js",
      "../../utils/normalize-secret-input.js",
      "./types.js"
    ],
    "external": [],
    "standard": []
  },
  "functions": [
    {
      "name": "collectSkillBins",
      "line": 26,
      "doc": "No documentation",
      "is_public": false,
      "is_async": false
    }
  ],
  "classes": [],
  "complexity_score": 34,
  "responsibility": {
    "single_responsibility_score": 0.6,
    "cohesion_indicators": [],
    "concerns": [
      "Multiple concerns detected: database, api, business_logic, logging"
    ],
    "detected_concerns": [
      "database",
      "api",
      "business_logic",
      "logging"
    ]
  }
}