{
  "path": "src/plugin-sdk/file-lock.ts",
  "extension": ".ts",
  "size_bytes": 4644,
  "line_count": 163,
  "documentation": {
    "file_docstring": null,
    "header_comments": [],
    "inline_comments": [],
    "todo_comments": [],
    "has_readme_style_header": false
  },
  "purpose": {
    "primary_role": "unknown",
    "secondary_roles": [],
    "confidence": 0.0,
    "indicators": []
  },
  "exports": [],
  "imports": {
    "internal": [
      "../shared/pid-alive.js",
      "../shared/process-scoped-map.js"
    ],
    "external": [
      "node:fs/promises",
      "node:path"
    ],
    "standard": []
  },
  "functions": [
    {
      "name": "computeDelayMs",
      "line": 31,
      "doc": "No documentation",
      "is_public": false,
      "is_async": false
    },
    {
      "name": "readLockPayload",
      "line": 40,
      "doc": "No documentation",
      "is_public": false,
      "is_async": true
    },
    {
      "name": "resolveNormalizedFilePath",
      "line": 53,
      "doc": "No documentation",
      "is_public": false,
      "is_async": true
    },
    {
      "name": "isStaleLock",
      "line": 65,
      "doc": "No documentation",
      "is_public": false,
      "is_async": true
    },
    {
      "name": "releaseHeldLock",
      "line": 89,
      "doc": "No documentation",
      "is_public": false,
      "is_async": true
    },
    {
      "name": "acquireFileLock",
      "line": 104,
      "doc": "",
      "is_public": true,
      "is_async": true
    },
    {
      "name": "withFileLock",
      "line": 152,
      "doc": "",
      "is_public": true,
      "is_async": true
    }
  ],
  "classes": [
    {
      "name": "FileLockOptions",
      "line": 6,
      "doc": "No documentation",
      "is_public": true,
      "kind": "type_alias"
    },
    {
      "name": "LockFilePayload",
      "line": 17,
      "doc": "No documentation",
      "is_public": false,
      "kind": "type_alias"
    },
    {
      "name": "HeldLock",
      "line": 22,
      "doc": "No documentation",
      "is_public": false,
      "kind": "type_alias"
    },
    {
      "name": "FileLockHandle",
      "line": 84,
      "doc": "No documentation",
      "is_public": true,
      "kind": "type_alias"
    }
  ],
  "complexity_score": 21,
  "responsibility": {
    "single_responsibility_score": 1.0,
    "cohesion_indicators": [],
    "concerns": [],
    "detected_concerns": [
      "business_logic",
      "logging"
    ]
  }
}