{
  "path": "src/cli/daemon-cli/status.gather.ts",
  "extension": ".ts",
  "size_bytes": 13317,
  "line_count": 433,
  "documentation": {
    "file_docstring": null,
    "header_comments": [],
    "inline_comments": [],
    "todo_comments": [],
    "has_readme_style_header": false
  },
  "purpose": {
    "primary_role": "unknown",
    "secondary_roles": [],
    "confidence": 0.0,
    "indicators": []
  },
  "exports": [
    "renderPortDiagnosticsForCli",
    "resolvePortListeningAddresses"
  ],
  "imports": {
    "internal": [
      "../../daemon/diagnostics.js",
      "../../daemon/inspect.js",
      "../../daemon/inspect.js",
      "../../daemon/service-audit.js",
      "../../daemon/service-audit.js",
      "../../daemon/service-runtime.js",
      "../../daemon/service.js",
      "../../gateway/credentials.js",
      "../../gateway/net.js",
      "../../gateway/probe-auth.js",
      "../../infra/parse-finite-number.js",
      "../../infra/tailnet.js",
      "../../infra/tls/gateway.js",
      "./probe.js",
      "./restart-health.js",
      "./shared.js",
      "./types.js"
    ],
    "external": [],
    "standard": []
  },
  "functions": [
    {
      "name": "shouldReportPortUsage",
      "line": 124,
      "doc": "No documentation",
      "is_public": false,
      "is_async": false
    },
    {
      "name": "parseGatewaySecretRefPathFromError",
      "line": 134,
      "doc": "No documentation",
      "is_public": false,
      "is_async": false
    },
    {
      "name": "loadDaemonConfigContext",
      "line": 138,
      "doc": "No documentation",
      "is_public": false,
      "is_async": true
    },
    {
      "name": "resolveGatewayStatusSummary",
      "line": 190,
      "doc": "No documentation",
      "is_public": false,
      "is_async": true
    },
    {
      "name": "toPortStatusSummary",
      "line": 233,
      "doc": "No documentation",
      "is_public": false,
      "is_async": false
    },
    {
      "name": "inspectDaemonPortStatuses",
      "line": 247,
      "doc": "No documentation",
      "is_public": false,
      "is_async": true
    },
    {
      "name": "gatherDaemonStatus",
      "line": 263,
      "doc": "No documentation",
      "is_public": true,
      "is_async": true
    },
    {
      "name": "renderPortDiagnosticsForCli",
      "line": 412,
      "doc": "No documentation",
      "is_public": true,
      "is_async": false
    },
    {
      "name": "resolvePortListeningAddresses",
      "line": 424,
      "doc": "No documentation",
      "is_public": true,
      "is_async": false
    }
  ],
  "classes": [
    {
      "name": "ConfigSummary",
      "line": 36,
      "doc": "No documentation",
      "is_public": false,
      "kind": "type_alias"
    },
    {
      "name": "GatewayStatusSummary",
      "line": 44,
      "doc": "No documentation",
      "is_public": false,
      "kind": "type_alias"
    },
    {
      "name": "PortStatusSummary",
      "line": 54,
      "doc": "No documentation",
      "is_public": false,
      "kind": "type_alias"
    },
    {
      "name": "DaemonConfigContext",
      "line": 61,
      "doc": "No documentation",
      "is_public": false,
      "kind": "type_alias"
    },
    {
      "name": "ResolvedGatewayStatus",
      "line": 70,
      "doc": "No documentation",
      "is_public": false,
      "kind": "type_alias"
    },
    {
      "name": "DaemonStatus",
      "line": 77,
      "doc": "No documentation",
      "is_public": true,
      "kind": "type_alias"
    }
  ],
  "complexity_score": 53,
  "responsibility": {
    "single_responsibility_score": 0.6,
    "cohesion_indicators": [],
    "concerns": [
      "Multiple concerns detected: ui, business_logic, auth, logging"
    ],
    "detected_concerns": [
      "ui",
      "business_logic",
      "auth",
      "logging"
    ]
  }
}