{
  "path": "src/line/bot.ts",
  "extension": ".ts",
  "size_bytes": 2565,
  "line_count": 83,
  "documentation": {
    "file_docstring": null,
    "header_comments": [],
    "inline_comments": [],
    "todo_comments": [],
    "has_readme_style_header": false
  },
  "purpose": {
    "primary_role": "unknown",
    "secondary_roles": [],
    "confidence": 0.0,
    "indicators": []
  },
  "exports": [
    "createLineBot",
    "createLineWebhookCallback"
  ],
  "imports": {
    "internal": [
      "../auto-reply/reply/history.js",
      "../config/config.js",
      "../config/config.js",
      "../globals.js",
      "../runtime.js",
      "./accounts.js",
      "./bot-handlers.js",
      "./bot-message-context.js",
      "./types.js",
      "./webhook.js"
    ],
    "external": [
      "@line/bot-sdk",
      "express"
    ],
    "standard": []
  },
  "functions": [
    {
      "name": "createLineBot",
      "line": 29,
      "doc": "No documentation",
      "is_public": true,
      "is_async": false
    },
    {
      "name": "handleWebhook",
      "line": 48,
      "doc": "No documentation",
      "is_public": false,
      "is_async": true
    },
    {
      "name": "createLineWebhookCallback",
      "line": 71,
      "doc": "No documentation",
      "is_public": true,
      "is_async": false
    }
  ],
  "classes": [
    {
      "name": "LineBotOptions",
      "line": 14,
      "doc": "No documentation",
      "is_public": true,
      "kind": "interface"
    },
    {
      "name": "LineBot",
      "line": 24,
      "doc": "No documentation",
      "is_public": true,
      "kind": "interface"
    }
  ],
  "complexity_score": 5,
  "responsibility": {
    "single_responsibility_score": 0.6,
    "cohesion_indicators": [],
    "concerns": [
      "Multiple concerns detected: api, business_logic, auth, logging"
    ],
    "detected_concerns": [
      "api",
      "business_logic",
      "auth",
      "logging"
    ]
  }
}