{
  "path": "src/secrets/target-registry-pattern.ts",
  "extension": ".ts",
  "size_bytes": 5841,
  "line_count": 214,
  "documentation": {
    "file_docstring": null,
    "header_comments": [],
    "inline_comments": [],
    "todo_comments": [],
    "has_readme_style_header": false
  },
  "purpose": {
    "primary_role": "unknown",
    "secondary_roles": [],
    "confidence": 0.0,
    "indicators": []
  },
  "exports": [
    "expandPathTokens",
    "compileTargetRegistryEntry",
    "matchPathTokens",
    "materializePathTokens",
    "parsePathPattern"
  ],
  "imports": {
    "internal": [
      "./shared.js",
      "./target-registry-types.js"
    ],
    "external": [],
    "standard": []
  },
  "functions": [
    {
      "name": "countDynamicPatternTokens",
      "line": 22,
      "doc": "No documentation",
      "is_public": false,
      "is_async": false
    },
    {
      "name": "parsePathPattern",
      "line": 26,
      "doc": "No documentation",
      "is_public": true,
      "is_async": false
    },
    {
      "name": "compileTargetRegistryEntry",
      "line": 43,
      "doc": "No documentation",
      "is_public": true,
      "is_async": false
    },
    {
      "name": "matchPathTokens",
      "line": 66,
      "doc": "No documentation",
      "is_public": true,
      "is_async": false
    },
    {
      "name": "materializePathTokens",
      "line": 104,
      "doc": "No documentation",
      "is_public": true,
      "is_async": false
    },
    {
      "name": "expandPathTokens",
      "line": 134,
      "doc": "No documentation",
      "is_public": true,
      "is_async": false
    }
  ],
  "classes": [
    {
      "name": "PathPatternToken",
      "line": 4,
      "doc": "No documentation",
      "is_public": true,
      "kind": "type_alias"
    },
    {
      "name": "CompiledTargetRegistryEntry",
      "line": 9,
      "doc": "No documentation",
      "is_public": true,
      "kind": "type_alias"
    },
    {
      "name": "ExpandedPathMatch",
      "line": 16,
      "doc": "No documentation",
      "is_public": true,
      "kind": "type_alias"
    }
  ],
  "complexity_score": 37,
  "responsibility": {
    "single_responsibility_score": 1.0,
    "cohesion_indicators": [],
    "concerns": [],
    "detected_concerns": [
      "auth",
      "logging"
    ]
  }
}