{
  "path": "src/commands/doctor-memory-search.ts",
  "extension": ".ts",
  "size_bytes": 8653,
  "line_count": 233,
  "documentation": {
    "file_docstring": "Check whether memory search has a usable embedding provider. Runs as part of `openclaw doctor` \u2014 config-only, no network calls.",
    "header_comments": [],
    "inline_comments": [
      "QMD backend handles embeddings internally (e.g. embeddinggemma) \u2014 no",
      "separate embedding provider is needed. Skip the provider check entirely.",
      "If a specific provider is configured (not \"auto\"), check only that one.",
      "Model path looks valid (explicit file, hf: URL, or default model).",
      "If a gateway probe is available and reports not-ready, warn anyway \u2014",
      "the model download or node-llama-cpp setup may have failed at runtime.",
      "Remote provider \u2014 check for API key",
      "provider === \"auto\": check all providers in resolution order",
      "Check whether local embeddings are available. When `useDefaultFallback` is true (explicit `provider: \"local\"`), an empty modelPath is treated as available because the runtime falls back to DEFAULT_LOCAL_MODEL (an auto-downloaded HuggingFace model). When false (provider: \"auto\"), we only consider local available if the user explicitly configured a local file path \u2014 matching `canAutoSelectLocal()` in the runtime, which skips local for empty/hf: model paths.",
      "Remote/downloadable models (hf: or http:) aren't pre-resolved on disk,",
      "so we can't confirm availability without a network call. Treat as",
      "potentially available \u2014 the user configured it intentionally.",
      "Map embedding provider names to model-auth provider names"
    ],
    "todo_comments": [],
    "has_readme_style_header": false
  },
  "purpose": {
    "primary_role": "unknown",
    "secondary_roles": [],
    "confidence": 0.0,
    "indicators": []
  },
  "exports": [],
  "imports": {
    "internal": [
      "../agents/agent-scope.js",
      "../agents/memory-search.js",
      "../agents/model-auth.js",
      "../cli/command-format.js",
      "../config/config.js",
      "../memory/backend-config.js",
      "../memory/embeddings.js",
      "../memory/secret-input.js",
      "../terminal/note.js",
      "../utils.js"
    ],
    "external": [
      "node:fs"
    ],
    "standard": []
  },
  "functions": [
    {
      "name": "noteMemorySearchHealth",
      "line": 17,
      "doc": "Check whether memory search has a usable embedding provider.   Runs as part of `openclaw doctor` \u2014 config-only, no netwo",
      "is_public": true,
      "is_async": true
    },
    {
      "name": "hasLocalEmbeddings",
      "line": 169,
      "doc": "Check whether local embeddings are available.     When `useDefaultFallback` is true (explicit `provider: \"local\"`), an e",
      "is_public": false,
      "is_async": false
    },
    {
      "name": "hasApiKeyForProvider",
      "line": 189,
      "doc": "No documentation",
      "is_public": false,
      "is_async": true
    },
    {
      "name": "providerEnvVar",
      "line": 204,
      "doc": "No documentation",
      "is_public": false,
      "is_async": false
    },
    {
      "name": "buildGatewayProbeWarning",
      "line": 217,
      "doc": "No documentation",
      "is_public": false,
      "is_async": false
    }
  ],
  "classes": [],
  "complexity_score": 35,
  "responsibility": {
    "single_responsibility_score": 0.6,
    "cohesion_indicators": [],
    "concerns": [
      "Multiple concerns detected: api, auth, logging"
    ],
    "detected_concerns": [
      "api",
      "auth",
      "logging"
    ]
  }
}