{
  "path": "src/cli/command-secret-gateway.ts",
  "extension": ".ts",
  "size_bytes": 21225,
  "line_count": 644,
  "documentation": {
    "file_docstring": null,
    "header_comments": [],
    "inline_comments": [
      "Fall through to original gateway-specific error reporting."
    ],
    "todo_comments": [],
    "has_readme_style_header": false
  },
  "purpose": {
    "primary_role": "unknown",
    "secondary_roles": [],
    "confidence": 0.0,
    "indicators": []
  },
  "exports": [],
  "imports": {
    "internal": [
      "../config/config.js",
      "../config/types.secrets.js",
      "../gateway/call.js",
      "../gateway/protocol/index.js",
      "../secrets/path-utils.js",
      "../secrets/resolve.js",
      "../secrets/runtime-config-collectors.js",
      "../secrets/runtime-shared.js",
      "../secrets/runtime-web-tools.js",
      "../secrets/secret-value.js",
      "../secrets/shared.js",
      "../utils/message-channel.js"
    ],
    "external": [],
    "standard": []
  },
  "functions": [
    {
      "name": "normalizeCommandSecretResolutionMode",
      "line": 66,
      "doc": "No documentation",
      "is_public": false,
      "is_async": false
    },
    {
      "name": "enforcesResolvedSecrets",
      "line": 78,
      "doc": "No documentation",
      "is_public": false,
      "is_async": false
    },
    {
      "name": "dedupeDiagnostics",
      "line": 82,
      "doc": "No documentation",
      "is_public": false,
      "is_async": false
    },
    {
      "name": "targetsRuntimeWebPath",
      "line": 96,
      "doc": "No documentation",
      "is_public": false,
      "is_async": false
    },
    {
      "name": "targetsRuntimeWebResolution",
      "line": 100,
      "doc": "No documentation",
      "is_public": false,
      "is_async": false
    },
    {
      "name": "collectConfiguredTargetRefPaths",
      "line": 120,
      "doc": "No documentation",
      "is_public": false,
      "is_async": false
    },
    {
      "name": "classifyConfiguredTargetRefs",
      "line": 143,
      "doc": "No documentation",
      "is_public": false,
      "is_async": false
    },
    {
      "name": "parseGatewaySecretsResolveResult",
      "line": 200,
      "doc": "No documentation",
      "is_public": false,
      "is_async": false
    },
    {
      "name": "collectInactiveSurfacePathsFromDiagnostics",
      "line": 216,
      "doc": "No documentation",
      "is_public": false,
      "is_async": false
    },
    {
      "name": "isUnsupportedSecretsResolveError",
      "line": 232,
      "doc": "No documentation",
      "is_public": false,
      "is_async": false
    },
    {
      "name": "resolveCommandSecretRefsLocally",
      "line": 245,
      "doc": "No documentation",
      "is_public": false,
      "is_async": true
    },
    {
      "name": "buildTargetStatesByPath",
      "line": 346,
      "doc": "No documentation",
      "is_public": false,
      "is_async": false
    },
    {
      "name": "buildUnresolvedDiagnostics",
      "line": 363,
      "doc": "No documentation",
      "is_public": false,
      "is_async": false
    },
    {
      "name": "scrubUnresolvedAssignments",
      "line": 377,
      "doc": "No documentation",
      "is_public": false,
      "is_async": false
    },
    {
      "name": "filterInactiveSurfaceDiagnostics",
      "line": 386,
      "doc": "No documentation",
      "is_public": false,
      "is_async": false
    },
    {
      "name": "resolveTargetSecretLocally",
      "line": 401,
      "doc": "No documentation",
      "is_public": false,
      "is_async": true
    },
    {
      "name": "resolveCommandSecretRefsViaGateway",
      "line": 451,
      "doc": "No documentation",
      "is_public": true,
      "is_async": true
    }
  ],
  "classes": [
    {
      "name": "ResolveCommandSecretsResult",
      "line": 22,
      "doc": "No documentation",
      "is_public": false,
      "kind": "type_alias"
    },
    {
      "name": "CommandSecretResolutionMode",
      "line": 29,
      "doc": "No documentation",
      "is_public": true,
      "kind": "type_alias"
    },
    {
      "name": "LegacyCommandSecretResolutionMode",
      "line": 34,
      "doc": "No documentation",
      "is_public": false,
      "kind": "type_alias"
    },
    {
      "name": "CommandSecretResolutionModeInput",
      "line": 36,
      "doc": "No documentation",
      "is_public": false,
      "kind": "type_alias"
    },
    {
      "name": "CommandSecretTargetState",
      "line": 40,
      "doc": "No documentation",
      "is_public": true,
      "kind": "type_alias"
    },
    {
      "name": "GatewaySecretsResolveResult",
      "line": 46,
      "doc": "No documentation",
      "is_public": false,
      "kind": "type_alias"
    }
  ],
  "complexity_score": 66,
  "responsibility": {
    "single_responsibility_score": 0.6,
    "cohesion_indicators": [],
    "concerns": [
      "Multiple concerns detected: database, api, business_logic, logging"
    ],
    "detected_concerns": [
      "database",
      "api",
      "business_logic",
      "logging"
    ]
  }
}