{
  "path": "vendor/a2ui/renderers/lit/src/0.8/ui/directives/sanitizer.ts",
  "extension": ".ts",
  "size_bytes": 1336,
  "line_count": 40,
  "documentation": {
    "file_docstring": null,
    "header_comments": [],
    "inline_comments": [
      "This is only safe for (and intended to be used for) text node positions. If you are using attribute position, then this is only safe if the attribute value is surrounded by double-quotes, and is unsafe otherwise (because the value could break out of the attribute value and e.g. add another attribute)."
    ],
    "todo_comments": [],
    "has_readme_style_header": false
  },
  "purpose": {
    "primary_role": "unknown",
    "secondary_roles": [],
    "confidence": 0.0,
    "indicators": []
  },
  "exports": [
    "escapeNodeText",
    "unescapeNodeText"
  ],
  "imports": {
    "internal": [],
    "external": [
      "lit"
    ],
    "standard": []
  },
  "functions": [
    {
      "name": "escapeNodeText",
      "line": 25,
      "doc": "This is only safe for (and intended to be used for) text node positions. If   you are using attribute position, then thi",
      "is_public": true,
      "is_async": false
    },
    {
      "name": "unescapeNodeText",
      "line": 32,
      "doc": "No documentation",
      "is_public": true,
      "is_async": false
    }
  ],
  "classes": [],
  "complexity_score": 4,
  "responsibility": {
    "single_responsibility_score": 0.6,
    "cohesion_indicators": [],
    "concerns": [
      "Multiple concerns detected: ui, api, auth"
    ],
    "detected_concerns": [
      "ui",
      "api",
      "auth"
    ]
  }
}